odoo8_addon_sale_quotation_sourcing_stock_route_transit-8.0.0.1.0.99.dev11-py3.8-nspkg.pth
odoo_addons/sale_quotation_sourcing_stock_route_transit/README.rst
odoo_addons/sale_quotation_sourcing_stock_route_transit/__init__.py
odoo_addons/sale_quotation_sourcing_stock_route_transit/__openerp__.py
odoo_addons/sale_quotation_sourcing_stock_route_transit/i18n/ca.po
odoo_addons/sale_quotation_sourcing_stock_route_transit/i18n/de.po
odoo_addons/sale_quotation_sourcing_stock_route_transit/i18n/es.po
odoo_addons/sale_quotation_sourcing_stock_route_transit/i18n/fr.po
odoo_addons/sale_quotation_sourcing_stock_route_transit/i18n/it.po
odoo_addons/sale_quotation_sourcing_stock_route_transit/i18n/nl_NL.po
odoo_addons/sale_quotation_sourcing_stock_route_transit/i18n/pt_BR.po
odoo_addons/sale_quotation_sourcing_stock_route_transit/i18n/ro.po
odoo_addons/sale_quotation_sourcing_stock_route_transit/i18n/sale_quotation_sourcing_stock_route_transit.pot
odoo_addons/sale_quotation_sourcing_stock_route_transit/i18n/sk.po
odoo_addons/sale_quotation_sourcing_stock_route_transit/i18n/sl.po
odoo_addons/sale_quotation_sourcing_stock_route_transit/i18n/tr.po
odoo_addons/sale_quotation_sourcing_stock_route_transit/i18n/tr_TR.po
odoo_addons/sale_quotation_sourcing_stock_route_transit/model/__init__.py
odoo_addons/sale_quotation_sourcing_stock_route_transit/model/sale_order_line.py
odoo_addons/sale_quotation_sourcing_stock_route_transit/static/description/icon.png
odoo_addons/sale_quotation_sourcing_stock_route_transit/tests/__init__.py
odoo_addons/sale_quotation_sourcing_stock_route_transit/tests/test_sourced_by.py
odoo8_addon_sale_quotation_sourcing_stock_route_transit-8.0.0.1.0.99.dev11.dist-info/METADATA
odoo8_addon_sale_quotation_sourcing_stock_route_transit-8.0.0.1.0.99.dev11.dist-info/WHEEL
odoo8_addon_sale_quotation_sourcing_stock_route_transit-8.0.0.1.0.99.dev11.dist-info/namespace_packages.txt
odoo8_addon_sale_quotation_sourcing_stock_route_transit-8.0.0.1.0.99.dev11.dist-info/top_level.txt
odoo8_addon_sale_quotation_sourcing_stock_route_transit-8.0.0.1.0.99.dev11.dist-info/RECORD
