Metadata-Version: 2.1
Name: odoo8-addon-sale-quotation-sourcing-stock-route-transit
Version: 8.0.0.1.0.99.dev11
Summary: Link module for sale_quotation_sourcing + stock_route_transit
Home-page: http://www.camptocamp.com
Author: Camptocamp,Odoo Community Association (OCA)
Author-email: support@odoo-community.org
License: UNKNOWN
Platform: UNKNOWN
Classifier: Programming Language :: Python
Classifier: Framework :: Odoo
Classifier: Framework :: Odoo :: 8.0
Requires-Python: ~=2.7
Requires-Dist: odoo8-addon-sale-quotation-sourcing
Requires-Dist: odoo8-addon-stock-route-transit
Requires-Dist: odoo (<9.0a,>=8.0a)
